maxrf4u/__init__.py
maxrf4u/_modidx.py
maxrf4u/_nbdev.py
maxrf4u/absorption.py
maxrf4u/calibration.py
maxrf4u/fingerprints.py
maxrf4u/hotmax.py
maxrf4u/interactive_visualization.py
maxrf4u/iplotting.py
maxrf4u/peak_pattern_puzzle_solver.py
maxrf4u/peakmaps.py
maxrf4u/peakpuzzle.py
maxrf4u/speckles.py
maxrf4u/storage.py
maxrf4u/warp.py
maxrf4u/xphysics.py
maxrf4u-0.1.27.dist-info/LICENSE
maxrf4u-0.1.27.dist-info/METADATA
maxrf4u-0.1.27.dist-info/WHEEL
maxrf4u-0.1.27.dist-info/entry_points.txt
maxrf4u-0.1.27.dist-info/top_level.txt
maxrf4u-0.1.27.dist-info/RECORD
