Metadata-Version: 2.1
Name: maxrf4u
Version: 0.1.27
Summary: Explore your X-Ray Fluorescence spectral images
Home-page: https://github.com/fligt/maxrf4u
Author: Frank Ligterink
Author-email: frank.ligterink@gmail.com
License: GNU General Public License v3
Keywords: ma-xrf
Classifier: Development Status :: 3 - Alpha
Classifier: Intended Audience :: Developers
Classifier: Natural Language :: English
Classifier: Programming Language :: Python :: 3.7
Classifier: Programming Language :: Python :: 3.8
Classifier: Programming Language :: Python :: 3.9
Classifier: Programming Language :: Python :: 3.10
Classifier: License :: OSI Approved :: GNU General Public License v3 (GPLv3)
Requires-Python: >=3.7
License-File: LICENSE
Requires-Dist: fisx
Requires-Dist: numpy
Requires-Dist: dask[complete]
Requires-Dist: dask-image
Requires-Dist: zarr
Requires-Dist: IPython
Requires-Dist: opencv-python
Requires-Dist: matplotlib
Requires-Dist: scipy
Requires-Dist: ipywidgets
Requires-Dist: ipyleaflet
Requires-Dist: scikit-image
Requires-Dist: imageio
Requires-Dist: mendeleev
Requires-Dist: moseley
Requires-Dist: scikit-learn
Requires-Dist: xraydb
Requires-Dist: Pillow
Provides-Extra: dev
